faastapi/__init__.py
faastapi/cli/__init__.py
faastapi/cli/cli.py
faastapi/cli/functions.py
faastapi/cli/generator.py
faastapi/cli/jobs.py
faastapi/cli/plugins.py
faastapi/cli/template_model.py
faastapi/cli/test.py
faastapi/context.py
faastapi/databases/__init__.py
faastapi/databases/async_sql.py
faastapi/databases/models.py
faastapi/databases/mongodb.py
faastapi/databases/redis.py
faastapi/databases/sql.py
faastapi/exceptions.py
faastapi/faastapi.py
faastapi/instrumentation/__init__.py
faastapi/instrumentation/process_time.py
faastapi/logger.py
faastapi/security/__init__.py
faastapi/security/basic_auth.py
faastapi/security/cors.py
faastapi/security/models.py
faastapi/security/oauth2_password_bearer.py
faastapi/temp.py
faastapi/templates/.dockerignore.j2
faastapi/templates/.env.yml.j2
faastapi/templates/Dockerfile.j2
faastapi/templates/function.yml.j2
faastapi/templates/main.py.j2
faastapi/templates/models.py.j2
faastapi-0.3.4.dist-info/entry_points.txt
faastapi-0.3.4.dist-info/LICENSE
faastapi-0.3.4.dist-info/WHEEL
faastapi-0.3.4.dist-info/METADATA
faastapi-0.3.4.dist-info/RECORD
