Metadata-Version: 2.1
Name: faastapi
Version: 0.3.4
Summary: Easily create OpenFaas functions built on top of FastAPI Python framework
Home-page: https://monsoon-gitlab.iti.gr/cap-dev/faastapi
License: MIT
Author: Carlos Benavides
Author-email: carlos.benavides@capgemini.com
Requires-Python: >=3.6,<4.0
Classifier: License :: OSI Approved :: MIT License
Classifier: Programming Language :: Python :: 3
Classifier: Programming Language :: Python :: 3.6
Classifier: Programming Language :: Python :: 3.7
Provides-Extra: all
Provides-Extra: async-mysql
Provides-Extra: async-postgres
Provides-Extra: async-sqlite
Provides-Extra: cli
Provides-Extra: mongodb
Provides-Extra: mysql
Provides-Extra: oauth
Provides-Extra: postgres
Provides-Extra: redis
Provides-Extra: sqlite
Requires-Dist: PyJWT (>=1.7,<2.0); extra == "oauth" or extra == "all"
Requires-Dist: aiomysql (>=0.0.20,<0.0.21); extra == "async-mysql" or extra == "all"
Requires-Dist: aiosqlite (>=0.10.0,<0.11.0); extra == "async-sqlite" or extra == "all"
Requires-Dist: asyncpg (>=0.18.3,<0.19.0); extra == "async-postgres" or extra == "all"
Requires-Dist: bcrypt (>=3.1,<4.0); extra == "oauth" or extra == "all"
Requires-Dist: click (>=7.0,<8.0); extra == "cli" or extra == "all"
Requires-Dist: databases (>=0.2.5,<0.3.0); extra == "async-mysql" or extra == "async-postgres" or extra == "async-sqlite"
Requires-Dist: fastapi (>=0.33.0,<0.34.0)
Requires-Dist: jinja2 (>=2.10,<3.0); extra == "cli" or extra == "all"
Requires-Dist: mysqlclient (>=1.4,<2.0); extra == "mysql" or extra == "all"
Requires-Dist: passlib (>=1.7,<2.0); extra == "oauth" or extra == "all"
Requires-Dist: psycopg2 (>=2.8,<3.0); extra == "postgres" or extra == "all"
Requires-Dist: pymongo (>=3.8,<4.0); extra == "mongodb" or extra == "all"
Requires-Dist: python-multipart (>=0.0.5,<0.0.6); extra == "oauth" or extra == "all"
Requires-Dist: pyyaml (>=5.1,<6.0); extra == "cli" or extra == "all"
Requires-Dist: redis (>=3.3,<4.0); extra == "redis" or extra == "all"
Requires-Dist: sqlalchemy (>=1.3,<2.0); extra == "sqlite" or extra == "mysql" or extra == "postgres" or extra == "all"
Requires-Dist: uvicorn (>=0.8.6,<0.9.0)
